{
    "details": [
        { "path": "examples/plotting/file/iris.py",          "name": "iris"                                        },
        { "path": "examples/plotting/file/image_rgba.py",    "name": "image_rgba"                                  },
        { "path": "examples/plotting/file/candlestick.py",   "name": "candlestick"                                 },
        { "path": "examples/plotting/file/legend.py",        "name": "legend"                                      },
        { "path": "examples/plotting/file/correlation.py",   "name": "correlation"                                 },
        { "path": "examples/plotting/file/glucose.py",       "name": "glucose"                                     },
        { "path": "examples/plotting/file/les_mis.py",       "name": "les_mis"                                     },
        { "path": "examples/plotting/file/unemployment.py",  "name": "unemployment"                                },
        { "path": "examples/plotting/file/stocks.py",        "name": "stocks"                                      },
        { "path": "examples/plotting/file/vector.py",        "name": "streamline"                                  },
        { "path": "examples/plotting/file/vector.py",        "name": "quiver"                                      },
        { "path": "examples/plotting/file/categorical.py",   "name": "categorical"                                 },
        { "path": "examples/plotting/file/periodic.py",      "name": "periodic"                                    },
        { "path": "examples/plotting/file/histogram.py",     "name": "histogram"                                   },
        { "path": "examples/plotting/file/image.py",         "name": "image"                                       },
        { "path": "examples/plotting/file/lorenz.py",        "name": "lorenz"                                      },
        { "path": "examples/plotting/file/color_scatter.py", "name": "color_scatter"                               },
        { "path": "examples/glyphs/iris_splom.py",           "name": "iris_splom",             "symbol": "grid"    },
        { "path": "examples/glyphs/anscombe.py",             "name": "anscombe",               "symbol": "grid"    },
        { "path": "examples/plotting/file/choropleth.py",    "name": "choropleth"                                  },
        { "path": "examples/plotting/file/texas.py",         "name": "texas"                                       },
        { "path": "examples/plotting/file/markers.py",       "name": "scatter"                                     },
        { "path": "examples/plotting/file/burtin.py",        "name": "burtin"                                      },
        { "path": "examples/plotting/file/brewer.py",        "name": "brewer"                                      },
        { "path": "examples/plotting/file/elements.py",      "name": "elements"                                    },
        { "path": "examples/plotting/file/boxplot.py",       "name": "boxplot"                                     },
        { "path": "examples/charts/area.py",                 "name": "area_chart"                                  },
        { "path": "examples/charts/boxplot.py",              "name": "boxplot_chart"                               },
        { "path": "examples/charts/cat_heatmap.py",          "name": "cat_heatmap_chart"                           },
        { "path": "examples/charts/donut.py",                "name": "donut_chart"                                 },
        { "path": "examples/charts/dots.py",                 "name": "dot_chart"                                   },
        { "path": "examples/charts/histograms.py",           "name": "histograms_chart"                            },
        { "path": "examples/charts/iris_scatter.py",         "name": "iris_scatter_chart"                          },
        { "path": "examples/charts/lines.py",                "name": "line_chart"                                  },
        { "path": "examples/charts/stacked_bar.py",          "name": "stacked_bar_chart"                           },
        { "path": "examples/charts/steps.py",                "name": "step_chart"                                  },
        { "path": "examples/charts/stocks_timeseries.py",    "name": "stocks_timeseries_chart"                     },
        { "path": "examples/compat/ggplot/density.py",       "name": "density"                                     },
        { "path": "examples/compat/ggplot/line.py",          "name": "ggplot_line"                                 },
        { "path": "examples/compat/ggplot/step.py",          "name": "step"                                        },
        { "path": "examples/compat/ggplot/xkcd_density.py",  "name": "xkcd_density"                                },
        { "path": "examples/compat/seaborn/violin.py",       "name": "violin"                                      },
        { "path": "examples/compat/seaborn/kde.py",          "name": "kde"                                         },
        { "path": "examples/compat/seaborn/sinerror.py",     "name": "sinerror"                                    }
    ]
}
